ustatus/__init__.py
ustatus/components/__init__.py
ustatus/components/drawing/battery_icon.py
ustatus/components/module.py
ustatus/components/modules/__init__.py
ustatus/components/modules/battery.py
ustatus/components/modules/clock.py
ustatus/components/modules/gpu.py
ustatus/components/modules/test.py
ustatus/components/modules/volume.py
ustatus/config.py
ustatus/cpuinfo.py
ustatus/docgen.py
ustatus/graphics/__init__.py
ustatus/graphics/bar_graph.py
ustatus/graphics/line_graph.py
ustatus/graphics/meter.py
ustatus/graphics/volume.py
ustatus/hooks/__init__.py
ustatus/hooks/use_timer.py
ustatus/main.py
ustatus/module.py
ustatus/modules/__init__.py
ustatus/modules/cpu_module.py
ustatus/modules/mpris_module.py
ustatus/modules/power_module.py
ustatus/modules/power_profiles_module.py
ustatus/modules/sway_module.py
ustatus/modules/tray_module.py
ustatus/modules/volume_module.py
ustatus/remote_service.py
ustatus/schema.py
ustatus/ustatus.py
ustatus/utils/__init__.py
ustatus/utils/notifications.py
ustatus/utils/power_utils.py
ustatus/utils/swaymsg.py
ustatus-0.1.10.dist-info/entry_points.txt
ustatus-0.1.10.dist-info/WHEEL
ustatus-0.1.10.dist-info/METADATA
ustatus-0.1.10.dist-info/RECORD
