Metadata-Version: 2.1
Name: ustatus
Version: 0.1.10
Summary: GTK-based status window for wayland shells.
Home-page: https://github.com/mbrea-c/ustatus
Author: Manuel Brea
Author-email: m.brea.carreras@gmail.com
Requires-Python: >=3.10,<4.0
Classifier: Programming Language :: Python :: 3
Classifier: Programming Language :: Python :: 3.10
Requires-Dist: PyGObject (>=3.42.0,<4.0.0)
Requires-Dist: dbus-next (>=0.2.3,<0.3.0)
Requires-Dist: gbulb (>=0.6.2,<0.7.0)
Requires-Dist: jsonschema (>=4.4.0,<5.0.0)
Requires-Dist: psutil (==5.8.0)
Requires-Dist: pulsectl (>=22.3.2,<23.0.0)
Requires-Dist: pulsectl-asyncio (>=0.2.0,<0.3.0)
Requires-Dist: python-dbus-system-api (>=0.1.0,<0.2.0)
Requires-Dist: python-reactive-ui (>=0.2.9,<0.3.0)
Requires-Dist: tomli (>=1.2.2,<2.0.0)
